_orphanage_poll.abi3.so
orphanage/poll.py
orphanage/poll_build.py
orphanage/poll.c
orphanage/poll.h
orphanage/__init__.py
orphanage-0.1.0.dist-info/RECORD
orphanage-0.1.0.dist-info/top_level.txt
orphanage-0.1.0.dist-info/METADATA
orphanage-0.1.0.dist-info/WHEEL
