Metadata-Version: 2.1
Name: orphanage
Version: 0.1.0
Summary: Let orphan processes suicide
Home-page: https://github.com/tonyseek/python-orphanage
Author: Jiangge Zhang
Author-email: tonyseek@gmail.com
License: MIT
Keywords: process,management,orphan
Platform: POSIX
Platform: Linux
Classifier: Development Status :: 3 - Alpha
Classifier: Intended Audience :: Developers
Classifier: Intended Audience :: System Administrators
Classifier: License :: OSI Approved :: MIT License
Classifier: Operating System :: POSIX
Classifier: Operating System :: POSIX :: Linux
Classifier: Programming Language :: Python :: 2.7
Classifier: Programming Language :: Python :: 3
Classifier: Programming Language :: Python :: Implementation :: CPython
Classifier: Programming Language :: Python :: Implementation :: PyPy
Classifier: Topic :: Software Development :: Libraries :: Python Modules
Classifier: Topic :: Utilities
Requires-Dist: cffi (>=1.0.0)
